Core/DaoBase.py
Core/EntityBase.py
Core/HttpManager.py
Core/JobBase.py
Core/Log.py
Core/Proxy.py
Core/QaBase.py
Core/__init__.py
PySQL/__init__.py
Test/TestAction.py
Test/TestDao.py
Test/TestEntity.py
Test/TestQa.py
Test/__init__.py
Util/CSVHelper.py
Util/DateTimeHelper.py
Util/DictHelper.py
Util/DingDingHelper.py
Util/DumperHelper.py
Util/EmailHelper.py
Util/JobHelper.py
Util/MongoHelper.py
Util/MySqlHelper.py
Util/NumericHelper.py
Util/S3Helper.py
Util/StringHelper.py
Util/__init__.py
degree72_simple-0.0.69.dist-info/METADATA
degree72_simple-0.0.69.dist-info/WHEEL
degree72_simple-0.0.69.dist-info/top_level.txt
degree72_simple-0.0.69.dist-info/RECORD
